Workbook

Sheet ReadMe
A1: TCS — 3-Statement DCF Model
A4: How the model is organized?
A5: 1. Assumptions | B5: Every forecast driver lives here (growth, margins, tax, WACC inputs). Change a yellow cell and the whole model recalculates.
A7: 2. Income Statement | B7: FY22-FY26 are actual TCS consolidated results (source: screener.in / TCS filings). FY27E-FY31E are forecast from Assumptions.
A9: 3. Balance Sheet | B9: Same historical/forecast split. Forecast lines are driven off Revenue using ratios from Assumptions.
A11: 4. Cash Flow Statement | B11: Historical actuals, then a forecast built with the indirect method (Net Profit + D&A - change in working capital, etc.).
A13: 5. DCF & Valuation | B13: Builds Free Cash Flow to Firm (FCFF) from the Income Statement, discounts it at WACC, and derives an implied share price.
A15: 6. Sensitivity | B15: A WACC x Terminal Growth grid showing how the implied share price moves — the standard DCF sanity check.
A18: Color legend (standard finance-model convention)
A19: ■ Sample | B19: Blue Text - a hardcoded number (a historical actual, or a typed-in assumption)
A20: ■ Sample | B20: Black Text - a formula that calculates from other cells on the SAME sheet
A21: ■ Sample | B21: Green Text - a formula that pulls from ANOTHER sheet
A22: ■ Sample | B22: Yellow Fill - a key assumption you're meant to edit and play with
A23: ■ Sample | B23: Light Blue Fill - a subtotal / total row
A24: ■ Sample | B24: Light Red Fill - a balance/sanity check to watch
A27: Data sources
A28: 1) Historical Income Statement, Balance Sheet, Cash Flow (FY22-FY26): www.screener.in/company/TCS/consolidated (consolidated Ind AS figures, ₹ Crores), cross-checked against TCS Q4 FY25/FY26 results releases.
A29: 2) Current share price (₹1,983) and market cap (₹7,16,423 Cr): screener.in, close of 1 Jul 2026.
A30: 3) India 10-year G-Sec yield (6.75%): tradingeconomics.com / capera.co, as of early Jul 2026.
A31: 4) Shares outstanding (~362 Cr): TCS equity share capital (face value ₹1) as of FY26.
A34: Limitations
A35: 1) Beta (0.65) and Equity Risk Premium (7.0%) are reasonable placeholders for an Indian IT bellwether - based on TCS's actual 5Y beta (e.g. on screener.in or a terminal) and Aswath Damodaran's latest India ERP.
A36: 2) Revenue growth tapering from 8% to 6% and EBITDA margin held at 27% are judgment calls based on the last 5 years - can be adjusted for a stronger view (deal pipeline, AI-led disruption risk, etc).
A37: 3) The Balance Sheet's 'Balance Check' row will NOT be exactly zero in the forecast years. That's intentional - Other Assets and Other Liabilities are both forecast independently off Revenue, so they rarely tie perfectly. In a real model, the gap gets absorbed by a cash/revolver 'plug'.
A40: How to use this Model?
A41: This workbook is built so that one change on the Assumptions tab ripples through all six other tabs automatically.
A43: Quick experiments to try! (watch DCF Valuation!D29, the implied share price, after each one)
A45: Change | B45: On Tab | C45: What to observe?
A46: Revenue Growth % (Row 6) | B46: Assumptions | C46: How much a 1-2 point change in near-term growth moves the share price vs. Terminal Growth
A47: EBITDA Margin % (Row 7) | B47: Assumptions | C47: Margin compression hits every forecast year at once — watch how fast value erodes
A48: Beta (C23) | B48: Assumptions | C48: Watch WACC (C31) rise or fall, then see how that alone swings the valuation
A49: Terminal Growth Rate (C35) | B49: Assumptions | C49: Small changes here move price more than similar changes to near-term growth — this is why Terminal Value is 65-85% of Enterprise Value
A50: Capex % of Revenue (Row () | B50: Assumptions | C50: Higher capex lowers FCFF directly — check Cash Flow tab’s Free Cash Flow line too
A53: Goal Seek
A54: To find what growth rate the market is implicitly pricing in at the current share price, use Data → What-If Analysis → Goal Seek: set DCF Valuation!D29 to 1983 (or whatever the live price is), by changing Assumptions!C6. This solves for the assumption instead of you guessing it.
A57: Caution
A58: If Terminal Growth Rate ever approaches or exceeds WACC, the Terminal Value formula breaks down (division by a near-zero or negative number) — keep a gap of at least 3-4 percentage points between the two.
A61: Refer
A62: Refer to the Base Case Assumptions table on 'Assumptions' Tab to find the original Operating Assumptions after experimenting.

Sheet Assumptions
A1: Assumptions
A2: All operating assumptions apply to the forecast years FY27E-FY31E only. | L2: Base Case Assumptions
B4: Operating Assumptions | M4: FY27E | N4: FY28E | O4: FY29E | P4: FY30E | Q4: FY31E
C5: FY27E | D5: FY28E | E5: FY29E | F5: FY30E | G5: FY31E | L5: Revenue Growth % | M5: 0.08 | N5: 0.07 | O5: 0.065 | P5: 0.06 | Q5: 0.06
B6: Revenue Growth % | C6: 0.08 | D6: 0.07 | E6: 0.065 | F6: 0.06 | G6: 0.06 | L6: EBITDA Margin % | M6: 0.27 | N6: 0.27 | O6: 0.27 | P6: 0.27 | Q6: 0.27
B7: EBITDA Margin % | C7: 0.27 | D7: 0.27 | E7: 0.27 | F7: 0.27 | G7: 0.27 | L7: D&A % of Revenue | M7: 0.021 | N7: 0.021 | O7: 0.021 | P7: 0.021 | Q7: 0.021
B8: D&A % of Revenue | C8: 0.021 | D8: 0.021 | E8: 0.021 | F8: 0.021 | G8: 0.021 | L8: Capex % of Revenue | M8: 0.035 | N8: 0.035 | O8: 0.035 | P8: 0.035 | Q8: 0.035
B9: Capex % of Revenue | C9: 0.035 | D9: 0.035 | E9: 0.035 | F9: 0.035 | G9: 0.035 | L9: Capital WIP % of Revenue | M9: 0.01 | N9: 0.01 | O9: 0.01 | P9: 0.01 | Q9: 0.01
B10: Capital WIP % of Revenue | C10: 0.01 | D10: 0.01 | E10: 0.01 | F10: 0.01 | G10: 0.01 | L10: Investments % of Revenue | M10: 0.13 | N10: 0.13 | O10: 0.13 | P10: 0.13 | Q10: 0.13
B11: Investments % of Revenue | C11: 0.13 | D11: 0.13 | E11: 0.13 | F11: 0.13 | G11: 0.13 | L11: Other Assets % of Revenue | M11: 0.41 | N11: 0.41 | O11: 0.41 | P11: 0.41 | Q11: 0.41
B12: Other Assets % of Revenue | C12: 0.41 | D12: 0.41 | E12: 0.41 | F12: 0.41 | G12: 0.41 | L12: Other Liabilities % of Revenue | M12: 0.215 | N12: 0.215 | O12: 0.215 | P12: 0.215 | Q12: 0.215
B13: Other Liabilities % of Revenue | C13: 0.215 | D13: 0.215 | E13: 0.215 | F13: 0.215 | G13: 0.215 | L13: Borrowings % of Revenue | M13: 0.04 | N13: 0.04 | O13: 0.04 | P13: 0.04 | Q13: 0.04
B14: Borrowings % of Revenue | C14: 0.04 | D14: 0.04 | E14: 0.04 | F14: 0.04 | G14: 0.04 | L14: Other Income % of Revenue | M14: 0.015 | N14: 0.015 | O14: 0.015 | P14: 0.015 | Q14: 0.015
B15: Other Income % of Revenue | C15: 0.015 | D15: 0.015 | E15: 0.015 | F15: 0.015 | G15: 0.015 | L15: Tax Rate % | M15: 0.25 | N15: 0.25 | O15: 0.25 | P15: 0.25 | Q15: 0.25
B16: Tax Rate % | C16: 0.25 | D16: 0.25 | E16: 0.25 | F16: 0.25 | G16: 0.25 | L16: Dividend Payout % of Net Profit | M16: 0.8 | N16: 0.8 | O16: 0.8 | P16: 0.8 | Q16: 0.8
B17: Dividend Payout % of Net Profit | C17: 0.8 | D17: 0.8 | E17: 0.8 | F17: 0.8 | G17: 0.8
L18: A copy of the 'Operating Assumptions' to refer after experimenting.
B19: Cost of Capital (WACC) Assumptions
B21: Risk-Free Rate (10Y India G-Sec) | C21: 0.0675
B22: Equity Risk Premium - India | C22: 0.07
B23: Beta (TCS vs Nifty 50) | C23: 0.65
B24: Cost of Equity (Rf+Beta*ERP) | C24: =C21+C23*C22 -> 0.113
B25: Pre-Tax Cost of Debt | C25: 0.08
B26: Post-Tax Cost of Debt | C26: =C25*(1-C16) -> 0.06
B27: Market Value of Equity (₹ Cr) | C27: 716423
B28: Total Debt (₹ Cr, FY26) | C28: ='Balance Sheet'!G7 -> 11283
B29: Weight of Equity | C29: =C27/(C27+C28) -> 0.98449511
B30: Weight of Debt | C30: =1-C29 -> 0.015504888
B31: WACC | C31: =C29*C24+C30*C26 -> 0.11217824
B33: Terminal Value & Market Data
B35: Terminal Growth Rate (g) | C35: 0.05
B36: Current Share Price (₹) | C36: 1983
B37: Shares Outstanding (cr, FY26) | C37: ='Balance Sheet'!G4 -> 362

Sheet Income Statement
A1: TCS - Income Statement (Consolidated, Rs. in Crores)
C3: FY22 | D3: FY23 | E3: FY24 | F3: FY25 | G3: FY26 | H3: FY27E | I3: FY28E | J3: FY29E | K3: FY30E | L3: FY31E
B4: Revenue | C4: 191754 | D4: 225458 | E4: 240893 | F4: 255324 | G4: 267021 | H4: =G4*(1+Assumptions!C6) -> 288382.68 | I4: =H4*(1+Assumptions!D6) -> 308569.47 | J4: =I4*(1+Assumptions!E6) -> 328626.48 | K4: =J4*(1+Assumptions!F6) -> 348344.07 | L4: =K4*(1+Assumptions!G6) -> 369244.72
B5: Revenue Growth % | D5: =(D4-C4)/C4 -> 0.17576687 | E5: =(E4-D4)/D4 -> 0.068460645 | F5: =(F4-E4)/E4 -> 0.059906265 | G5: =(G4-F4)/F4 -> 0.04581238 | H5: =(H4-G4)/G4 -> 0.08 | I5: =(I4-H4)/H4 -> 0.07 | J5: =(J4-I4)/I4 -> 0.065 | K5: =(K4-J4)/J4 -> 0.06 | L5: =(L4-K4)/K4 -> 0.06
B6: EBITDA (Operating Profit) | C6: 53057 | D6: 59259 | E6: 64296 | F6: 67407 | G6: 72398 | H6: =H4*Assumptions!C7 -> 77863.324 | I6: =I4*Assumptions!D7 -> 83313.756 | J6: =J4*Assumptions!E7 -> 88729.15 | K6: =K4*Assumptions!F7 -> 94052.899 | L6: =L4*Assumptions!G7 -> 99696.073
B7: EBITDA Margin % | C7: =C6/C4 -> 0.27669305 | D7: =D6/D4 -> 0.26283831 | E7: =E6/E4 -> 0.26690688 | F7: =F6/F4 -> 0.26400573 | G7: =G6/G4 -> 0.27113223 | H7: =H6/H4 -> 0.27 | I7: =I6/I4 -> 0.27 | J7: =J6/J4 -> 0.27 | ... L7: =L6/L4 -> 0.27
B8: Depreciation & Amortization | C8: 4604 | D8: 5022 | E8: 4985 | F8: 5242 | G8: 5560 | H8: =H4*Assumptions!C8 -> 6056.0363 | I8: =I4*Assumptions!D8 -> 6479.9588 | J8: =J4*Assumptions!E8 -> 6901.1561 | K8: =K4*Assumptions!F8 -> 7315.2255 | L8: =L4*Assumptions!G8 -> 7754.139
B9: EBIT | C9: =C6-C8 -> 48453 | D9: =D6-D8 -> 54237 | E9: =E6-E8 -> 59311 | F9: =F6-F8 -> 62165 | G9: =G6-G8 -> 66838 | H9: =H6-H8 -> 71807.287 | I9: =I6-I8 -> 76833.797 | J9: =J6-J8 -> 81827.994 | ... L9: =L6-L8 -> 91941.934
B10: EBIT Margin % | C10: =C9/C4 -> 0.25268313 | D10: =D9/D4 -> 0.24056365 | E10: =E9/E4 -> 0.24621305 | F10: =F9/F4 -> 0.24347496 | G10: =G9/G4 -> 0.2503099 | H10: =H9/H4 -> 0.249 | I10: =I9/I4 -> 0.249 | J10: =J9/J4 -> 0.249 | ... L10: =L9/L4 -> 0.249
B11: Other Income | C11: 4018 | D11: 3449 | E11: 3464 | F11: 3962 | G11: -124 | H11: =H4*Assumptions!C15 -> 4325.7402 | I11: =I4*Assumptions!D15 -> 4628.542 | J11: =J4*Assumptions!E15 -> 4929.3972 | K11: =K4*Assumptions!F15 -> 5225.1611 | L11: =L4*Assumptions!G15 -> 5538.6707
B12: Interest Expense | C12: 784 | D12: 779 | E12: 778 | F12: 796 | G12: 1227 | H12: =AVERAGE('Balance Sheet'!G7+'Balance Sheet'!G9,'Balance Sheet'!H7+'Balance Sheet'!H9)*Assumptions!$C$25 -> 990.40649 | I12: =AVERAGE('Balance Sheet'!H7+'Balance Sheet'!H9,'Balance Sheet'!I7+'Balance Sheet'!I9)*Assumptions!$C$25 -> 1038.9344 | J12: =AVERAGE('Balance Sheet'!I7+'Balance Sheet'!I9,'Balance Sheet'!J7+'Balance Sheet'!J9)*Assumptions!$C$25 -> 1025.6503 | K12: =AVERAGE('Balance Sheet'!J7+'Balance Sheet'!J9,'Balance Sheet'!K7+'Balance Sheet'!K9)*Assumptions!$C$25 -> 1083.1529 | L12: =AVERAGE('Balance Sheet'!K7+'Balance Sheet'!K9,'Balance Sheet'!L7+'Balance Sheet'!L9)*Assumptions!$C$25 -> 1148.1421
B13: Profit Before Tax | C13: =C9+C11-C12 -> 51687 | D13: =D9+D11-D12 -> 56907 | E13: =E9+E11-E12 -> 61997 | F13: =F9+F11-F12 -> 65331 | G13: =G9+G11-G12 -> 65487 | H13: =H9+H11-H12 -> 75142.621 | I13: =I9+I11-I12 -> 80423.405 | J13: =J9+J11-J12 -> 85731.741 | ... L13: =L9+L11-L12 -> 96332.463
B14: Tax Expense | C14: =C13-C16 -> 13238 | D14: =D13-D16 -> 14604 | E14: =E13-E16 -> 15898 | F14: =F13-F16 -> 16534 | G14: =G13-G16 -> 16033 | H14: =H13*Assumptions!C16 -> 18785.655 | I14: =I13*Assumptions!D16 -> 20105.851 | J14: =J13*Assumptions!E16 -> 21432.935 | K14: =K13*Assumptions!F16 -> 22719.921 | L14: =L13*Assumptions!G16 -> 24083.116
B15: Effective Tax Rate % | C15: =C14/C13 -> 0.25611856 | D15: =D14/D13 -> 0.25662924 | E15: =E14/E13 -> 0.25643176 | F15: =F14/F13 -> 0.25308047 | G15: =G14/G13 -> 0.24482722 | H15: =H14/H13 -> 0.25 | I15: =I14/I13 -> 0.25 | J15: =J14/J13 -> 0.25 | ... L15: =L14/L13 -> 0.25
B16: Net Profit | C16: 38449 | D16: 42303 | E16: 46099 | F16: 48797 | G16: 49454 | H16: =H13-H14 -> 56356.966 | I16: =I13-I14 -> 60317.554 | J16: =J13-J14 -> 64298.806 | K16: =K13-K14 -> 68159.762 | L16: =L13-L14 -> 72249.347
B17: Net Profit Margin % | C17: =C16/C4 -> 0.20051211 | D17: =D16/D4 -> 0.1876314 | E17: =E16/E4 -> 0.19136712 | F17: =F16/F4 -> 0.19111795 | G17: =G16/G4 -> 0.18520641 | H17: =H16/H4 -> 0.19542424 | I17: =I16/I4 -> 0.1954748 | J17: =J16/J4 -> 0.19565923 | ... L17: =L16/L4 -> 0.19566792
B18: Shares Outstanding (Cr) | C18: 366 | D18: 366 | E18: 362 | F18: 362 | G18: 362 | H18: =G18 -> 362 | I18: =H18 -> 362 | J18: =I18 -> 362 | K18: =J18 -> 362 | L18: =K18 -> 362
B19: EPS(₹) | C19: =C16/C18 -> 105.05191 | D19: =D16/D18 -> 115.58197 | E19: =E16/E18 -> 127.3453 | F19: =F16/F18 -> 134.79834 | G19: =G16/G18 -> 136.61326 | H19: =H16/H18 -> 155.68223 | I19: =I16/I18 -> 166.62308 | J19: =J16/J18 -> 177.62101 | ... L19: =L16/L18 -> 199.58383

Sheet Balance Sheet
A1: TCS - Balance Sheet (Consolidated, Rs. in Crores)
C3: FY22 | D3: FY23 | E3: FY24 | F3: FY25 | G3: FY26 | H3: FY27E | I3: FY28E | J3: FY29E | K3: FY30E | L3: FY31E
B4: Equity Share Capital | C4: 366 | D4: 366 | E4: 362 | F4: 362 | G4: 362 | H4: =G4 -> 362 | I4: =H4 -> 362 | J4: =I4 -> 362 | K4: =J4 -> 362 | L4: =K4 -> 362
B5: Reserves & Surplus | C5: 88773 | D5: 90058 | E5: 90127 | F5: 94394 | G5: 106878 | H5: =G5+'Income Statement'!H16*(1-Assumptions!C17) -> 118149.39 | I5: =H5+'Income Statement'!I16*(1-Assumptions!D17) -> 130212.9 | J5: =I5+'Income Statement'!J16*(1-Assumptions!E17) -> 143072.67 | K5: =J5+'Income Statement'!K16*(1-Assumptions!F17) -> 156704.62 | L5: =K5+'Income Statement'!L16*(1-Assumptions!G17) -> 171154.49
B6: Total Equity | C6: =C4+C5 -> 89139 | D6: =D4+D5 -> 90424 | E6: =E4+E5 -> 90489 | F6: =F4+F5 -> 94756 | G6: =G4+G5 -> 107240 | H6: =H4+H5 -> 118511.39 | I6: =I4+I5 -> 130574.9 | J6: =J4+J5 -> 143434.67 | ... L6: =L4+L5 -> 171516.49
B7: Borrowings (incl. lease liabilities) | C7: 7818 | D7: 7688 | E7: 8021 | F7: 9392 | G7: 11283 | H7: ='Income Statement'!H4*Assumptions!C14 -> 11535.307 | I7: ='Income Statement'!I4*Assumptions!D14 -> 12342.779 | J7: ='Income Statement'!J4*Assumptions!E14 -> 13145.059 | K7: ='Income Statement'!K4*Assumptions!F14 -> 13933.763 | L7: ='Income Statement'!L4*Assumptions!G14 -> 14769.789
B8: Other Liabilities | C8: 43967 | D8: 44747 | E8: 46962 | F8: 54501 | G8: 62644 | H8: ='Income Statement'!H4*Assumptions!C13 -> 62002.276 | I8: ='Income Statement'!I4*Assumptions!D13 -> 66342.436 | J8: ='Income Statement'!J4*Assumptions!E13 -> 70654.694 | K8: ='Income Statement'!K4*Assumptions!F13 -> 74893.975 | L8: ='Income Statement'!L4*Assumptions!G13 -> 79387.614
B9: Short-Term Borrowings/Revolver (Plug) | C9: 0 | D9: 0 | E9: 0 | F9: 0 | G9: 0 | H9: =MAX((H12+H13+H14+H15)-(H6+H7+H8),0) -> 1941.855 | I9: =MAX((I12+I13+I14+I15)-(I6+I7+I8),0) -> 153.4191 | J9: =MAX((J12+J13+J14+J15)-(J6+J7+J8),0) -> 0 | K9: =MAX((K12+K13+K14+K15)-(K6+K7+K8),0) -> 0 | L9: =MAX((L12+L13+L14+L15)-(L6+L7+L8),0) -> 0
B10: Total Liabilities | C10: =C6+C7+C8 -> 140924 | D10: =D6+D7+D8 -> 142859 | E10: =E6+E7+E8 -> 145472 | F10: =F6+F7+F8 -> 158649 | G10: =G6+G7+G8 -> 181167 | H10: =H6+H7+H8+H9 -> 193990.83 | I10: =I6+I7+I8+I9 -> 209413.54 | J10: =J6+J7+J8+J9 -> 227234.42 | K10: =K6+K7+K8+K9 -> 245894.36 | L10: =L6+L7+L8+L9 -> 265673.89
B12: Fixed Assets (Net) | C12: 21298 | D12: 20515 | E12: 19604 | F12: 23053 | G12: 31343 | H12: =G12+'Income Statement'!H4*Assumptions!C9-'Income Statement'!H8 -> 35380.358 | I12: =H12+'Income Statement'!I4*Assumptions!D9-'Income Statement'!I8 -> 39700.33 | J12: =I12+'Income Statement'!J4*Assumptions!E9-'Income Statement'!J8 -> 44301.101 | K12: =J12+'Income Statement'!K4*Assumptions!F9-'Income Statement'!K8 -> 49177.918 | L12: =K12+'Income Statement'!L4*Assumptions!G9-'Income Statement'!L8 -> 54347.344
B13: Capital Work-in-Progress | C13: 1205 | D13: 1234 | E13: 1564 | F13: 1546 | G13: 2665 | H13: ='Income Statement'!H4*Assumptions!C10 -> 2883.8268 | I13: ='Income Statement'!I4*Assumptions!D10 -> 3085.6947 | J13: ='Income Statement'!J4*Assumptions!E10 -> 3286.2648 | K13: ='Income Statement'!K4*Assumptions!F10 -> 3483.4407 | L13: ='Income Statement'!L4*Assumptions!G10 -> 3692.4472
B14: Investments | C14: 30485 | D14: 37163 | E14: 31762 | F14: 30964 | G14: 33988 | H14: ='Income Statement'!H4*Assumptions!C11 -> 37489.748 | I14: ='Income Statement'!I4*Assumptions!D11 -> 40114.031 | J14: ='Income Statement'!J4*Assumptions!E11 -> 42721.443 | K14: ='Income Statement'!K4*Assumptions!F11 -> 45284.729 | L14: ='Income Statement'!L4*Assumptions!G11 -> 48001.813
B15: Other Assets | C15: 87936 | D15: 83947 | E15: 92542 | F15: 103086 | G15: 113171 | H15: ='Income Statement'!H4*Assumptions!C12 -> 118236.9 | I15: ='Income Statement'!I4*Assumptions!D12 -> 126513.48 | J15: ='Income Statement'!J4*Assumptions!E12 -> 134736.86 | K15: ='Income Statement'!K4*Assumptions!F12 -> 142821.07 | L15: ='Income Statement'!L4*Assumptions!G12 -> 151390.33
B16: Cash & Cash Equivalents (Plug) | C16: 0 | D16: 0 | E16: 0 | F16: 0 | G16: 0 | H16: =MAX((H6+H7+H8)-(H12+H13+H14+H15),0) -> 0 | I16: =MAX((I6+I7+I8)-(I12+I13+I14+I15),0) -> 0 | J16: =MAX((J6+J7+J8)-(J12+J13+J14+J15),0) -> 2188.7518 | K16: =MAX((K6+K7+K8)-(K12+K13+K14+K15),0) -> 5127.1983 | L16: =MAX((L6+L7+L8)-(L12+L13+L14+L15),0) -> 8241.9517
B17: Total Assets | C17: =C12+C13+C14+C15+C16 -> 140924 | D17: =D12+D13+D14+D15+D16 -> 142859 | E17: =E12+E13+E14+E15+E16 -> 145472 | F17: =F12+F13+F14+F15+F16 -> 158649 | G17: =G12+G13+G14+G15+G16 -> 181167 | H17: =H12+H13+H14+H15+H16 -> 193990.83 | I17: =I12+I13+I14+I15+I16 -> 209413.54 | J17: =J12+J13+J14+J15+J16 -> 227234.42 | ... L17: =L12+L13+L14+L15+L16 -> 265673.89
B19: Balance Check (Total Assets − Total Liabilities) | C19: =C17-C10 -> 0 | D19: =D17-D10 -> 0 | E19: =E17-E10 -> 0 | F19: =F17-F10 -> 0 | G19: =G17-G10 -> 0 | H19: =H17-H10 -> 0 | I19: =I17-I10 -> 0 | J19: =J17-J10 -> 0 | ... L19: =L17-L10 -> 0
B22: Note: the forecast Balance Check is not zero by design — Other Assets and Other Liabilities are each forecast independently as a % of Revenue. See ReadMe for why, and how you could add a cash 'plug' to force an exact balance.

Sheet Cash Flow
A1: TCS - Cash Flow Statement (Consolidated, Rs. in Crores)
C3: FY22 | D3: FY23 | E3: FY24 | F3: FY25 | G3: FY26 | H3: FY27E | I3: FY28E | J3: FY29E | K3: FY30E | L3: FY31E
B4: Cash from Operating Activities | C4: 39949 | D4: 41965 | E4: 44338 | F4: 48908 | G4: 52094 | H4: ='Income Statement'!H16+'Income Statement'!H8-(('Balance Sheet'!H15-'Balance Sheet'!H8)-('Balance Sheet'!G15-'Balance Sheet'!G8)) -> 56705.379 | I4: ='Income Statement'!I16+'Income Statement'!I8-(('Balance Sheet'!I15-'Balance Sheet'!I8)-('Balance Sheet'!H15-'Balance Sheet'!H8)) -> 62861.089 | J4: ='Income Statement'!J16+'Income Statement'!J8-(('Balance Sheet'!J15-'Balance Sheet'!J8)-('Balance Sheet'!I15-'Balance Sheet'!I8)) -> 67288.844 | K4: ='Income Statement'!K16+'Income Statement'!K8-(('Balance Sheet'!K15-'Balance Sheet'!K8)-('Balance Sheet'!J15-'Balance Sheet'!J8)) -> 71630.057 | L4: ='Income Statement'!L16+'Income Statement'!L8-(('Balance Sheet'!L15-'Balance Sheet'!L8)-('Balance Sheet'!K15-'Balance Sheet'!K8)) -> 75927.861
B5: Cash from Investing Activities | C5: -738 | D5: 548 | E5: 6091 | F5: -2144 | G5: -11886 | H5: =-('Income Statement'!H4*Assumptions!C9)-('Balance Sheet'!H14-'Balance Sheet'!G14) -> -13595.142 | I5: =-('Income Statement'!I4*Assumptions!D9)-('Balance Sheet'!I14-'Balance Sheet'!H14) -> -13424.214 | J5: =-('Income Statement'!J4*Assumptions!E9)-('Balance Sheet'!J14-'Balance Sheet'!I14) -> -14109.339 | K5: =-('Income Statement'!K4*Assumptions!F9)-('Balance Sheet'!K14-'Balance Sheet'!J14) -> -14755.329 | L5: =-('Income Statement'!L4*Assumptions!G9)-('Balance Sheet'!L14-'Balance Sheet'!K14) -> -15640.649
B6: Cash from Financing Activities | C6: -33581 | D6: -47878 | E6: -48536 | F6: -47438 | G6: -42133 | H6: =-('Income Statement'!H16*Assumptions!C17)+('Balance Sheet'!H7-'Balance Sheet'!G7) -> -44833.265 | I6: =-('Income Statement'!I16*Assumptions!D17)+('Balance Sheet'!I7-'Balance Sheet'!H7) -> -47446.572 | J6: =-('Income Statement'!J16*Assumptions!E17)+('Balance Sheet'!J7-'Balance Sheet'!I7) -> -50636.764 | K6: =-('Income Statement'!K16*Assumptions!F17)+('Balance Sheet'!K7-'Balance Sheet'!J7) -> -53739.106 | L6: =-('Income Statement'!L16*Assumptions!G17)+('Balance Sheet'!L7-'Balance Sheet'!K7) -> -56963.452
B7: Net Cash Flow | C7: =C4+C5+C6 -> 5630 | D7: =D4+D5+D6 -> -5365 | E7: =E4+E5+E6 -> 1893 | F7: =F4+F5+F6 -> -674 | G7: =G4+G5+G6 -> -1925 | H7: =H4+H5+H6 -> -1723.0282 | I7: =I4+I5+I6 -> 1990.3037 | J7: =J4+J5+J6 -> 2542.741 | ... L7: =L4+L5+L6 -> 3323.7598
B8: Free Cash Flow (CFO − Capex) | C8: 36985 | D8: 38902 | E8: 41688 | F8: 44994 | G8: 48013 | H8: =H4-('Income Statement'!H4*Assumptions!C9) -> 46611.986 | I8: =I4-('Income Statement'!I4*Assumptions!D9) -> 52061.158 | J8: =J4-('Income Statement'!J4*Assumptions!E9) -> 55786.917 | K8: =K4-('Income Statement'!K4*Assumptions!F9) -> 59438.015 | L8: =L4-('Income Statement'!L4*Assumptions!G9) -> 63004.296
B10: Memo: Capex | D10: 4239 | E10: 4074 | F10: 8691 | G10: 13850 | H10: ='Income Statement'!H4*Assumptions!C9 -> 10093.394 | I10: ='Income Statement'!I4*Assumptions!D9 -> 10799.931 | J10: ='Income Statement'!J4*Assumptions!E9 -> 11501.927 | K10: ='Income Statement'!K4*Assumptions!F9 -> 12192.043 | L10: ='Income Statement'!L4*Assumptions!G9 -> 12923.565
B11: Memo: Dividends Paid | C11: 15764 | D11: 42303 | E11: 26737 | F11: 45869 | G11: 40058 | H11: ='Income Statement'!H16*Assumptions!C17 -> 45085.573 | I11: ='Income Statement'!I16*Assumptions!D17 -> 48254.043 | J11: ='Income Statement'!J16*Assumptions!E17 -> 51439.045 | K11: ='Income Statement'!K16*Assumptions!F17 -> 54527.809 | L11: ='Income Statement'!L16*Assumptions!G17 -> 57799.478
B13: Historical Capex and Dividends are back-derived (Capex = ΔFixed Assets + D&A; Dividends = Net Profit x reported payout %) since screener does not report them as separate line items.

Sheet DCF Valuation
A1: TCS - DCF Valuation
H3: FY27E | I3: FY28E | J3: FY29E | K3: FY30E | L3: FY31E
B4: EBIT | H4: ='Income Statement'!H9 -> 71807.287 | I4: ='Income Statement'!I9 -> 76833.797 | J4: ='Income Statement'!J9 -> 81827.994 | K4: ='Income Statement'!K9 -> 86737.674 | L4: ='Income Statement'!L9 -> 91941.934
B5: Tax Rate % | H5: =Assumptions!C16 -> 0.25 | I5: =Assumptions!D16 -> 0.25 | J5: =Assumptions!E16 -> 0.25 | K5: =Assumptions!F16 -> 0.25 | L5: =Assumptions!G16 -> 0.25
B6: NOPAT = EBIT*(1-Tax Rate) | H6: =H4*(1-H5) -> 53855.465 | I6: =I4*(1-I5) -> 57625.348 | J6: =J4*(1-J5) -> 61370.996 | K6: =K4*(1-K5) -> 65053.255 | L6: =L4*(1-L5) -> 68956.451
B7: Add: Depreciation & Amortization | H7: ='Income Statement'!H8 -> 6056.0363 | I7: ='Income Statement'!I8 -> 6479.9588 | J7: ='Income Statement'!J8 -> 6901.1561 | K7: ='Income Statement'!K8 -> 7315.2255 | L7: ='Income Statement'!L8 -> 7754.139
B8: Less: Capex | H8: ='Income Statement'!H4*Assumptions!C9 -> 10093.394 | I8: ='Income Statement'!I4*Assumptions!D9 -> 10799.931 | J8: ='Income Statement'!J4*Assumptions!E9 -> 11501.927 | K8: ='Income Statement'!K4*Assumptions!F9 -> 12192.043 | L8: ='Income Statement'!L4*Assumptions!G9 -> 12923.565
B9: Less: Increase in Net Working Capital | H9: =(('Balance Sheet'!H15-'Balance Sheet'!H8)-('Balance Sheet'!G15-'Balance Sheet'!G8)) -> 5707.6226 | I9: =(('Balance Sheet'!I15-'Balance Sheet'!I8)-('Balance Sheet'!H15-'Balance Sheet'!H8)) -> 3936.4236 | J9: =(('Balance Sheet'!J15-'Balance Sheet'!J8)-('Balance Sheet'!I15-'Balance Sheet'!I8)) -> 3911.118 | K9: =(('Balance Sheet'!K15-'Balance Sheet'!K8)-('Balance Sheet'!J15-'Balance Sheet'!J8)) -> 3844.9299 | L9: =(('Balance Sheet'!L15-'Balance Sheet'!L8)-('Balance Sheet'!K15-'Balance Sheet'!K8)) -> 4075.6256
B10: Free Cash Flow to Firm (FCFF) | H10: =H6+H7-H8-H9 -> 44110.485 | I10: =I6+I7-I8-I9 -> 49368.952 | J10: =J6+J7-J8-J9 -> 52859.107 | K10: =K6+K7-K8-K9 -> 56331.509 | L10: =L6+L7-L8-L9 -> 59711.399
B11: Discount Period (years) | H11: 1 | I11: 2 | J11: 3 | K11: 4 | L11: 5
B12: Discount Factor = 1/(1+WACC)^n | H12: =1/(1+$D$17)^H11 -> 0.89913645 | I12: =1/(1+$D$17)^I11 -> 0.80844636 | J12: =1/(1+$D$17)^J11 -> 0.7269036 | K12: =1/(1+$D$17)^K11 -> 0.65358552 | L12: =1/(1+$D$17)^L11 -> 0.58766257
B13: PV of FCFF | H13: =H10*H12 -> 39661.345 | I13: =I10*I12 -> 39912.15 | J13: =J10*J12 -> 38423.475 | K13: =K10*K12 -> 36817.458 | L13: =L10*L12 -> 35090.154
B16: Valuation Bridge
B17: WACC | D17: =Assumptions!C31 -> 0.11217824
B18: Terminal Growth Rate (g) | D18: =Assumptions!C35 -> 0.05
B19: Net Debt (Borrowings - Investments, FY26) | D19: ='Balance Sheet'!G7-'Balance Sheet'!G14 -> -22705
B20: Shares Outstanding (Cr) | D20: =Assumptions!C37 -> 362
B21: Current Market Price (₹) | D21: =Assumptions!C36 -> 1983
B23: Sum of PV of Explicit FCFF (FY27E-FY31E) | D23: =SUM(H13:L13) -> 189904.58
B24: Terminal Value (as of end FY31E) = FCFF_31*(1+g)/(WACC-g) | D24: =L10*(1+D18)/(D17-D18) -> 1008342.6
B25: PV of Terminal Value | D25: =D24*L12 -> 592565.2
B26: Enterprise Value | D26: =D23+D25 -> 782469.78
B27: Less: Net Debt | D27: =D19 -> -22705
B28: Equity Value | D28: =D26-D19 -> 805174.78
B29: Implied Value per Share (₹) | D29: =D28/D20 -> 2224.2397
B30: Current Market Price (₹) | D30: =D21 -> 1983
B31: Upside/(Downside) to Current Price | D31: =(D29-D30)/D30 -> 0.12165393
B32: Terminal Value as % of Enterprise Value (Sanity Check) | D32: =D25/D26 -> 0.75730107

Sheet Sensitivity
B3: Grid shows the DCF-implied share price for combinations of WACC (rows) and Terminal Growth Rate (columns).
B5: WACC \ Terminal g→ | C5: ='DCF Valuation'!D18+(-0.01) -> 0.04 | D5: ='DCF Valuation'!D18+(-0.005) -> 0.045 | E5: ='DCF Valuation'!D18+(0) -> 0.05 | F5: ='DCF Valuation'!D18+(0.005) -> 0.055 | G5: ='DCF Valuation'!D18+(0.01) -> 0.06
B6: ='DCF Valuation'!D17+(-0.01) -> 0.10217824 | C6: {=(SUMPRODUCT('DCF Valuation'!$H$10:$L$10,1/(1+$B6)^'DCF Valuation'!$H$11:$L$11)+('DCF Valuation'!$L$10*(1+C$5)/($B6-C$5))/(1+$B6)^'DCF Valuation'!$L$11-'DCF Valuation'!$D$19)/'DCF Valuation'!$D$20} -> 2297.6867 | D6: {=(SUMPRODUCT('DCF Valuation'!$H$10:$L$10,1/(1+$B6)^'DCF Valuation'!$H$11:$L$11)+('DCF Valuation'!$L$10*(1+D$5)/($B6-D$5))/(1+$B6)^'DCF Valuation'!$L$11-'DCF Valuation'!$D$19)/'DCF Valuation'!$D$20} -> 2454.8829 | E6: {=(SUMPRODUCT('DCF Valuation'!$H$10:$L$10,1/(1+$B6)^'DCF Valuation'!$H$11:$L$11)+('DCF Valuation'!$L$10*(1+E$5)/($B6-E$5))/(1+$B6)^'DCF Valuation'!$L$11-'DCF Valuation'!$D$19)/'DCF Valuation'!$D$20} -> 2642.206 | F6: {=(SUMPRODUCT('DCF Valuation'!$H$10:$L$10,1/(1+$B6)^'DCF Valuation'!$H$11:$L$11)+('DCF Valuation'!$L$10*(1+F$5)/($B6-F$5))/(1+$B6)^'DCF Valuation'!$L$11-'DCF Valuation'!$D$19)/'DCF Valuation'!$D$20} -> 2869.2343 | G6: {=(SUMPRODUCT('DCF Valuation'!$H$10:$L$10,1/(1+$B6)^'DCF Valuation'!$H$11:$L$11)+('DCF Valuation'!$L$10*(1+G$5)/($B6-G$5))/(1+$B6)^'DCF Valuation'!$L$11-'DCF Valuation'!$D$19)/'DCF Valuation'!$D$20} -> 3150.0887
B7: ='DCF Valuation'!D17+(-0.005) -> 0.10717824 | C7: {=(SUMPRODUCT('DCF Valuation'!$H$10:$L$10,1/(1+$B7)^'DCF Valuation'!$H$11:$L$11)+('DCF Valuation'!$L$10*(1+C$5)/($B7-C$5))/(1+$B7)^'DCF Valuation'!$L$11-'DCF Valuation'!$D$19)/'DCF Valuation'!$D$20} -> 2129.164 | D7: {=(SUMPRODUCT('DCF Valuation'!$H$10:$L$10,1/(1+$B7)^'DCF Valuation'!$H$11:$L$11)+('DCF Valuation'!$L$10*(1+D$5)/($B7-D$5))/(1+$B7)^'DCF Valuation'!$L$11-'DCF Valuation'!$D$19)/'DCF Valuation'!$D$20} -> 2260.5598 | E7: {=(SUMPRODUCT('DCF Valuation'!$H$10:$L$10,1/(1+$B7)^'DCF Valuation'!$H$11:$L$11)+('DCF Valuation'!$L$10*(1+E$5)/($B7-E$5))/(1+$B7)^'DCF Valuation'!$L$11-'DCF Valuation'!$D$19)/'DCF Valuation'!$D$20} -> 2414.9357 | F7: {=(SUMPRODUCT('DCF Valuation'!$H$10:$L$10,1/(1+$B7)^'DCF Valuation'!$H$11:$L$11)+('DCF Valuation'!$L$10*(1+F$5)/($B7-F$5))/(1+$B7)^'DCF Valuation'!$L$11-'DCF Valuation'!$D$19)/'DCF Valuation'!$D$20} -> 2598.8977 | G7: {=(SUMPRODUCT('DCF Valuation'!$H$10:$L$10,1/(1+$B7)^'DCF Valuation'!$H$11:$L$11)+('DCF Valuation'!$L$10*(1+G$5)/($B7-G$5))/(1+$B7)^'DCF Valuation'!$L$11-'DCF Valuation'!$D$19)/'DCF Valuation'!$D$20} -> 2821.8528
B8: ='DCF Valuation'!D17+(0) -> 0.11217824 | C8: {=(SUMPRODUCT('DCF Valuation'!$H$10:$L$10,1/(1+$B8)^'DCF Valuation'!$H$11:$L$11)+('DCF Valuation'!$L$10*(1+C$5)/($B8-C$5))/(1+$B8)^'DCF Valuation'!$L$11-'DCF Valuation'!$D$19)/'DCF Valuation'!$D$20} -> 1984.0213 | D8: {=(SUMPRODUCT('DCF Valuation'!$H$10:$L$10,1/(1+$B8)^'DCF Valuation'!$H$11:$L$11)+('DCF Valuation'!$L$10*(1+D$5)/($B8-D$5))/(1+$B8)^'DCF Valuation'!$L$11-'DCF Valuation'!$D$19)/'DCF Valuation'!$D$20} -> 2095.1909 | E8: {=(SUMPRODUCT('DCF Valuation'!$H$10:$L$10,1/(1+$B8)^'DCF Valuation'!$H$11:$L$11)+('DCF Valuation'!$L$10*(1+E$5)/($B8-E$5))/(1+$B8)^'DCF Valuation'!$L$11-'DCF Valuation'!$D$19)/'DCF Valuation'!$D$20} -> 2224.2397 | F8: {=(SUMPRODUCT('DCF Valuation'!$H$10:$L$10,1/(1+$B8)^'DCF Valuation'!$H$11:$L$11)+('DCF Valuation'!$L$10*(1+F$5)/($B8-F$5))/(1+$B8)^'DCF Valuation'!$L$11-'DCF Valuation'!$D$19)/'DCF Valuation'!$D$20} -> 2375.8581 | G8: {=(SUMPRODUCT('DCF Valuation'!$H$10:$L$10,1/(1+$B8)^'DCF Valuation'!$H$11:$L$11)+('DCF Valuation'!$L$10*(1+G$5)/($B8-G$5))/(1+$B8)^'DCF Valuation'!$L$11-'DCF Valuation'!$D$19)/'DCF Valuation'!$D$20} -> 2556.5343
B9: ='DCF Valuation'!D17+(0.005) -> 0.11717824 | C9: {=(SUMPRODUCT('DCF Valuation'!$H$10:$L$10,1/(1+$B9)^'DCF Valuation'!$H$11:$L$11)+('DCF Valuation'!$L$10*(1+C$5)/($B9-C$5))/(1+$B9)^'DCF Valuation'!$L$11-'DCF Valuation'!$D$19)/'DCF Valuation'!$D$20} -> 1857.7138 | D9: {=(SUMPRODUCT('DCF Valuation'!$H$10:$L$10,1/(1+$B9)^'DCF Valuation'!$H$11:$L$11)+('DCF Valuation'!$L$10*(1+D$5)/($B9-D$5))/(1+$B9)^'DCF Valuation'!$L$11-'DCF Valuation'!$D$19)/'DCF Valuation'!$D$20} -> 1952.7584 | E9: {=(SUMPRODUCT('DCF Valuation'!$H$10:$L$10,1/(1+$B9)^'DCF Valuation'!$H$11:$L$11)+('DCF Valuation'!$L$10*(1+E$5)/($B9-E$5))/(1+$B9)^'DCF Valuation'!$L$11-'DCF Valuation'!$D$19)/'DCF Valuation'!$D$20} -> 2061.9512 | F9: {=(SUMPRODUCT('DCF Valuation'!$H$10:$L$10,1/(1+$B9)^'DCF Valuation'!$H$11:$L$11)+('DCF Valuation'!$L$10*(1+F$5)/($B9-F$5))/(1+$B9)^'DCF Valuation'!$L$11-'DCF Valuation'!$D$19)/'DCF Valuation'!$D$20} -> 2188.7052 | G9: {=(SUMPRODUCT('DCF Valuation'!$H$10:$L$10,1/(1+$B9)^'DCF Valuation'!$H$11:$L$11)+('DCF Valuation'!$L$10*(1+G$5)/($B9-G$5))/(1+$B9)^'DCF Valuation'!$L$11-'DCF Valuation'!$D$19)/'DCF Valuation'!$D$20} -> 2337.6275
B10: ='DCF Valuation'!D17+(0.01) -> 0.12217824 | C10: {=(SUMPRODUCT('DCF Valuation'!$H$10:$L$10,1/(1+$B10)^'DCF Valuation'!$H$11:$L$11)+('DCF Valuation'!$L$10*(1+C$5)/($B10-C$5))/(1+$B10)^'DCF Valuation'!$L$11-'DCF Valuation'!$D$19)/'DCF Valuation'!$D$20} -> 1746.803 | D10: {=(SUMPRODUCT('DCF Valuation'!$H$10:$L$10,1/(1+$B10)^'DCF Valuation'!$H$11:$L$11)+('DCF Valuation'!$L$10*(1+D$5)/($B10-D$5))/(1+$B10)^'DCF Valuation'!$L$11-'DCF Valuation'!$D$19)/'DCF Valuation'!$D$20} -> 1828.804 | E10: {=(SUMPRODUCT('DCF Valuation'!$H$10:$L$10,1/(1+$B10)^'DCF Valuation'!$H$11:$L$11)+('DCF Valuation'!$L$10*(1+E$5)/($B10-E$5))/(1+$B10)^'DCF Valuation'!$L$11-'DCF Valuation'!$D$19)/'DCF Valuation'!$D$20} -> 1922.166 | F10: {=(SUMPRODUCT('DCF Valuation'!$H$10:$L$10,1/(1+$B10)^'DCF Valuation'!$H$11:$L$11)+('DCF Valuation'!$L$10*(1+F$5)/($B10-F$5))/(1+$B10)^'DCF Valuation'!$L$11-'DCF Valuation'!$D$19)/'DCF Valuation'!$D$20} -> 2029.4257 | G10: {=(SUMPRODUCT('DCF Valuation'!$H$10:$L$10,1/(1+$B10)^'DCF Valuation'!$H$11:$L$11)+('DCF Valuation'!$L$10*(1+G$5)/($B10-G$5))/(1+$B10)^'DCF Valuation'!$L$11-'DCF Valuation'!$D$19)/'DCF Valuation'!$D$20} -> 2153.9357
B12: Highlighted cell = base-case WACC and base-case terminal growth rate (matches the DCF Valuation tab).
